kafkacrypto/__init__.py
kafkacrypto/base.py
kafkacrypto/chain.py
kafkacrypto/chainserver.py
kafkacrypto/common_wrapper.py
kafkacrypto/confluent_kafka_wrapper.py
kafkacrypto/controller.py
kafkacrypto/crypto.py
kafkacrypto/cryptoexchange.py
kafkacrypto/cryptokey.py
kafkacrypto/cryptostore.py
kafkacrypto/exceptions.py
kafkacrypto/kafka_python_wrapper.py
kafkacrypto/kafkacryptostore.py
kafkacrypto/keygenerator.py
kafkacrypto/keys.py
kafkacrypto/message.py
kafkacrypto/provisioners.py
kafkacrypto/ratchet.py
kafkacrypto/utils.py
kafkacrypto-0.9.11.1.dist-info/LICENSE
kafkacrypto-0.9.11.1.dist-info/METADATA
kafkacrypto-0.9.11.1.dist-info/WHEEL
kafkacrypto-0.9.11.1.dist-info/top_level.txt
kafkacrypto-0.9.11.1.dist-info/RECORD
