Metadata-Version: 2.1
Name: kafkacrypto
Version: 0.9.11.1
Summary: Message layer security/crypto for Kafka
Home-page: https://github.com/tmcqueen-materials/kafkacrypto
Author: Tyrel M. McQueen
Author-email: tmcqueen-pypi@demoivre.com
License: GNU GPLv2
Keywords: kafka kafka-crypto kafka-security security crypo
Platform: UNKNOWN
Classifier: Programming Language :: Python :: 3
Classifier: License :: OSI Approved :: GNU General Public License v2 (GPLv2)
Classifier: Operating System :: OS Independent
Requires-Python: >=3.3
License-File: LICENSE
Requires-Dist: pysodium (>=0.7.5)
Requires-Dist: msgpack (>=1.0.0)
Requires-Dist: certifi
Requires-Dist: dirhash (>=0.2.1)
Provides-Extra: confluent-kafka
Requires-Dist: confluent-kafka (>=2) ; extra == 'confluent-kafka'
Provides-Extra: kafka-python
Requires-Dist: kafka-python (>=1.4.4) ; extra == 'kafka-python'
Provides-Extra: liboqs-python
Requires-Dist: liboqs-python (>=0.10.0) ; extra == 'liboqs-python'
Provides-Extra: pyspx_slhdsa
Requires-Dist: pyspx-slhdsa (>=0.5.1) ; extra == 'pyspx_slhdsa'
